<text xmlns="http://www.tei-c.org/ns/1.0" xmlns:mi="http://mova.institute/ns/corpora/0.1">
  <data>
    <chunk src="http://tyzhden.ua/Economics/190521">
      <gap/>
      <p>
        <w>Критерії</w>
        <w>зарахування</w>
        <w>тих</w>
        <w>чи</w>
        <w>інших</w>
        <w>громадян</w>
        <w>до</w>
        <pc>«</pc>
        <g/>
        <w>нового</w>
        <g/>
        <pc>»</pc>
        <w>середнього</w>
        <w>класу</w>
        <g/>
        <pc>,</pc>
        <w>а</w>
        <w>отже</w>
        <g/>
        <pc>,</pc>
        <w>й</w>
        <w>уявлення</w>
        <w>про</w>
        <w>його</w>
        <w>чисельність</w>
        <w>і</w>
        <w>структуру</w>
        <w>в</w>
        <w>сучасній</w>
        <w>Україні</w>
        <w>не</w>
        <w>менш</w>
        <w>розмиті</w>
        <g/>
        <pc>,</pc>
        <w>ніж</w>
        <w>у</w>
        <w>випадку</w>
        <w>з</w>
        <w>малими</w>
        <w>та</w>
        <w>середніми</w>
        <w>підприємцями</w>
        <g/>
        <pc>.</pc>
        <w>Проведене</w>
        <w>у</w>
        <w>2016</w>
        <w>році</w>
        <w>дослідження</w>
        <w>Держстату</w>
        <w>виявило</w>
        <g/>
        <pc>,</pc>
        <w>що</w>
        <w>в</w>
        <w>45</w>
        <g/>
        <pc>,</pc>
        <g/>
        <w>7</w>
        <g/>
        <w>%</w>
        <w>домогосподарств</w>
        <w>грошей</w>
        <w>було</w>
        <w>достатньо</w>
        <g/>
        <pc>,</pc>
        <w>але</w>
        <w>заощаджень</w>
        <w>не</w>
        <w>робили</w>
        <g/>
        <pc>,</pc>
        <w>43</w>
        <g/>
        <pc>,</pc>
        <g/>
        <w>2</w>
        <g/>
        <w>%</w>
        <w>постійно</w>
        <w>відмовляли</w>
        <w>собі</w>
        <w>в</w>
        <w>найнеобхіднішому</w>
        <g/>
        <pc>,</pc>
        <w>окрім</w>
        <w>харчування</w>
        <g/>
        <pc>.</pc>
        <w>Приблизно</w>
        <w>порівну</w>
        <w>виявилося</w>
        <w>тих</w>
        <g/>
        <pc>,</pc>
        <w>які</w>
        <w>мали</w>
        <w>достатньо</w>
        <w>грошей</w>
        <w>і</w>
        <w>робили</w>
        <w>заощадження</w>
        <pc>(</pc>
        <g/>
        <w>6</w>
        <g/>
        <pc>,</pc>
        <g/>
        <w>2</w>
        <g/>
        <w>%</w>
        <g/>
        <pc>)</pc>
        <g/>
        <pc>,</pc>
        <w>і</w>
        <w>тих</w>
        <g/>
        <pc>,</pc>
        <w>кому</w>
        <w>не</w>
        <w>вистачало</w>
        <w>навіть</w>
        <w>на</w>
        <w>харчування</w>
        <pc>(</pc>
        <g/>
        <w>4</w>
        <g/>
        <pc>,</pc>
        <g/>
        <w>9</w>
        <g/>
        <w>%</w>
        <g/>
        <pc>)</pc>
        <g/>
        <pc>.</pc>
        <w>У</w>
        <w>25</w>
        <g/>
        <pc>,</pc>
        <g/>
        <w>3</w>
        <g/>
        <w>%</w>
        <w>досліджених</w>
        <w>домогосподарств</w>
        <w>заявили</w>
        <g/>
        <pc>,</pc>
        <w>що</w>
        <w>в</w>
        <w>разі</w>
        <w>появи</w>
        <w>додаткових</w>
        <w>доходів</w>
        <w>заощадили</w>
        <w>б</w>
        <w>їх</w>
        <g/>
        <pc>,</pc>
        <w>а</w>
        <w>5</w>
        <g/>
        <pc>,</pc>
        <g/>
        <w>4</w>
        <g/>
        <w>%</w>
        <w>спрямували</w>
        <w>б</w>
        <w>на</w>
        <w>розвиток</w>
        <w>бізнесу</w>
        <g/>
        <pc>.</pc>
        <w>Водночас</w>
        <w>26</w>
        <g/>
        <pc>,</pc>
        <g/>
        <w>2</w>
        <g/>
        <w>%</w>
        <pc>—</pc>
        <w>на</w>
        <w>їжу</w>
        <g/>
        <pc>,</pc>
        <w>37</w>
        <g/>
        <pc>,</pc>
        <g/>
        <w>9</w>
        <g/>
        <w>%</w>
        <pc>—</pc>
        <w>на</w>
        <w>одяг</w>
        <w>та</w>
        <w>взуття</w>
        <g/>
        <pc>.</pc>
      </p>
      <p>
        <w>У</w>
        <w>відповідь</w>
        <w>на</w>
        <w>пряме</w>
        <w>запитання</w>
        <w>до</w>
        <pc>«</pc>
        <g/>
        <w>небідних</w>
        <g/>
        <pc>,</pc>
        <w>але</w>
        <w>ще</w>
        <w>не</w>
        <w>представників</w>
        <w>середнього</w>
        <w>класу</w>
        <g/>
        <pc>»</pc>
        <w>зарахували</w>
        <w>себе</w>
        <w>27</w>
        <g/>
        <w>%</w>
        <w>опитаних</w>
        <g/>
        <pc>,</pc>
        <w>до</w>
        <w>бідних</w>
        <pc>—</pc>
        <w>72</w>
        <g/>
        <pc>,</pc>
        <g/>
        <w>3</w>
        <g/>
        <w>%</w>
        <g/>
        <pc>.</pc>
        <w>Оскільки</w>
        <w>заможним</w>
        <w>не</w>
        <w>назвав</w>
        <w>себе</w>
        <w>жоден</w>
        <g/>
        <pc>,</pc>
        <w>а</w>
        <w>представниками</w>
        <w>середнього</w>
        <w>класу</w>
        <pc>—</pc>
        <w>лише</w>
        <w>0</w>
        <g/>
        <pc>,</pc>
        <g/>
        <w>7</w>
        <g/>
        <w>%</w>
        <g/>
        <pc>,</pc>
        <w>то</w>
        <w>ці</w>
        <w>0</w>
        <g/>
        <pc>,</pc>
        <g/>
        <w>7</w>
        <g/>
        <w>%</w>
        <w>можна</w>
        <w>вважати</w>
        <w>саме</w>
        <w>заможними</w>
        <g/>
        <pc>,</pc>
        <w>а</w>
        <w>27</w>
        <g/>
        <w>%</w>
        <pc>«</pc>
        <g/>
        <w>небідних</w>
        <g/>
        <pc>»</pc>
        <pc>—</pc>
        <w>українським</w>
        <w>середнім</w>
        <w>класом</w>
        <g/>
        <pc>,</pc>
        <w>який</w>
        <w>просто</w>
        <w>має</w>
        <w>завищені</w>
        <w>уявлення</w>
        <w>про</w>
        <w>рівень</w>
        <w>необхідних</w>
        <w>для</w>
        <w>цього</w>
        <w>доходів</w>
        <g/>
        <pc>.</pc>
        <w>Наприклад</w>
        <g/>
        <pc>,</pc>
        <w>у</w>
        <w>тих-таки</w>
        <w>США</w>
        <g/>
        <pc>,</pc>
        <w>за</w>
        <w>даними</w>
        <w>досліджень</w>
        <w>компанії</w>
        <w>Statista</w>
        <g/>
        <pc>,</pc>
        <w>щоб</w>
        <w>мати</w>
        <w>можливість</w>
        <w>піти</w>
        <w>у</w>
        <w>відпустку</w>
        <g/>
        <pc>,</pc>
        <w>54</w>
        <g/>
        <w>%</w>
        <w>респондентів</w>
        <w>змушені</w>
        <w>відмовлятися</w>
        <w>від</w>
        <w>придбання</w>
        <w>товарів</w>
        <w>довгострокового</w>
        <w>використання</w>
        <pc>(</pc>
        <g/>
        <w>телевізорів</w>
        <w>або</w>
        <w>електроніки</w>
        <g/>
        <pc>)</pc>
        <g/>
        <pc>,</pc>
        <w>а</w>
        <w>43</w>
        <g/>
        <w>%</w>
        <pc>—</pc>
        <w>від</w>
        <w>нового</w>
        <w>одягу</w>
        <w>та</w>
        <w>інших</w>
        <w>промтоварів</w>
        <g/>
        <pc>.</pc>
        <w>Доповідь</w>
        <w>Feeding</w>
        <w>America</w>
        <w>засвідчила</w>
        <g/>
        <pc>,</pc>
        <w>що</w>
        <w>66</w>
        <g/>
        <w>%</w>
        <w>домогосподарств</w>
        <w>мусили</w>
        <w>обирати</w>
        <w>між</w>
        <w>тим</w>
        <g/>
        <pc>,</pc>
        <w>витратити</w>
        <w>гроші</w>
        <w>на</w>
        <w>їжу</w>
        <w>чи</w>
        <w>на</w>
        <w>медичне</w>
        <w>обслуговування</w>
        <g/>
        <pc>.</pc>
      </p>
      <p>
        <w>Можна</w>
        <w>сказати</w>
        <g/>
        <pc>,</pc>
        <w>27</w>
        <g/>
        <w>%</w>
        <pc>«</pc>
        <g/>
        <w>небідних</w>
        <g/>
        <pc>»</pc>
        <w>українських</w>
        <w>домогосподарств</w>
        <w>корелюють</w>
        <w>із</w>
        <w>тими</w>
        <w>25</w>
        <g/>
        <pc>–</pc>
        <g/>
        <w>30</w>
        <g/>
        <w>%</w>
        <g/>
        <pc>,</pc>
        <w>які</w>
        <w>заощадили</w>
        <w>б</w>
        <w>додаткові</w>
        <w>доходи</w>
        <w>в</w>
        <w>разі</w>
        <w>їх</w>
        <w>появи</w>
        <w>та</w>
        <w>спрямували</w>
        <w>б</w>
        <w>на</w>
        <w>розвиток</w>
        <w>бізнесу</w>
        <g/>
        <pc>,</pc>
        <w>а</w>
        <w>також</w>
        <w>із</w>
        <w>часткою</w>
        <w>людей</w>
        <w>із</w>
        <w>середнім</w>
        <w>доходом</w>
        <w>відносно</w>
        <w>решти</w>
        <w>громадян</w>
        <g/>
        <pc>.</pc>
        <w>А</w>
        <w>на</w>
        <w>Заході</w>
        <g/>
        <pc>,</pc>
        <w>як</w>
        <w>відомо</w>
        <g/>
        <pc>,</pc>
        <w>середній</w>
        <w>клас</w>
        <w>виокремлюють</w>
        <w>не</w>
        <w>так</w>
        <w>за</w>
        <w>номінальним</w>
        <w>доходом</w>
        <g/>
        <pc>,</pc>
        <w>як</w>
        <w>відносно</w>
        <w>доходів</w>
        <w>решти</w>
        <g/>
        <pc>.</pc>
        <w>Наприклад</w>
        <g/>
        <pc>,</pc>
        <w>у</w>
        <w>США</w>
        <w>йдеться</w>
        <w>про</w>
        <w>домогосподарства</w>
        <g/>
        <pc>,</pc>
        <w>які</w>
        <w>мають</w>
        <w>від</w>
        <w>2</w>
        <w>до</w>
        <w>7,5</w>
        <w>прожиткового</w>
        <w>мінімуму</w>
        <w>на</w>
        <w>члена</w>
        <w>сім’ї</w>
        <g/>
        <pc>.</pc>
        <w>В</w>
        <w>Україні</w>
        <w>рівень</w>
        <w>середнього</w>
        <w>доходу</w>
        <w>на</w>
        <w>члена</w>
        <w>сім’ї</w>
        <w>понад</w>
        <w>два</w>
        <w>прожиткових</w>
        <w>мінімуми</w>
        <pc>(</pc>
        <g/>
        <w>без</w>
        <w>обмеження</w>
        <w>верхньої</w>
        <w>планки</w>
        <g/>
        <pc>)</pc>
        <w>у</w>
        <w>2015</w>
        <w>році</w>
        <w>мали</w>
        <w>31</w>
        <g/>
        <pc>,</pc>
        <g/>
        <w>2</w>
        <g/>
        <w>%</w>
        <w>мешканців</w>
        <pc>(</pc>
        <g/>
        <w>що</w>
        <w>зіставно</w>
        <w>із</w>
        <w>середнім</w>
        <w>класом</w>
        <w>за</w>
        <w>низкою</w>
        <w>інших</w>
        <w>наведених</w>
        <w>вище</w>
        <w>критеріїв</w>
        <g/>
        <pc>)</pc>
        <g/>
        <pc>.</pc>
        <w>Як</w>
        <w>бачимо</w>
        <g/>
        <pc>,</pc>
        <w>за</w>
        <w>цим</w>
        <w>критерієм</w>
        <w>людей</w>
        <w>середнього</w>
        <w>рівня</w>
        <w>доходів</w>
        <w>в</w>
        <w>українському</w>
        <w>суспільстві</w>
        <w>позаторік</w>
        <w>було</w>
        <w>майже</w>
        <w>вдвічі</w>
        <w>менше</w>
        <g/>
        <pc>,</pc>
        <w>ніж</w>
        <w>у</w>
        <w>США</w>
        <pc>(</pc>
        <g/>
        <w>55</w>
        <g/>
        <pc>,</pc>
        <g/>
        <w>6</w>
        <g/>
        <w>%</w>
        <g/>
        <pc>)</pc>
        <g/>
        <pc>.</pc>
        <w>А</w>
        <w>порівняння</w>
        <w>абсолютних</w>
        <w>доходів</w>
        <w>засвідчує</w>
        <g/>
        <pc>,</pc>
        <w>що</w>
        <w>український</w>
        <w>середній</w>
        <w>клас</w>
        <w>має</w>
        <w>дещо</w>
        <w>нижчий</w>
        <w>рівень</w>
        <w>життя</w>
        <g/>
        <pc>,</pc>
        <w>навіть</w>
        <w>якщо</w>
        <w>врахувати</w>
        <w>різну</w>
        <w>його</w>
        <w>вартість</w>
        <w>у</w>
        <w>двох</w>
        <w>країнах</w>
        <g/>
        <pc>.</pc>
      </p>
      <p>
        <w>За</w>
        <w>оцінкою</w>
        <w>МВФ</w>
        <g/>
        <pc>,</pc>
        <w>2015</w>
        <w>року</w>
        <w>ВВП</w>
        <w>у</w>
        <w>розрахунку</w>
        <w>на</w>
        <w>одну</w>
        <w>особу</w>
        <w>за</w>
        <w>паритетом</w>
        <w>купівельної</w>
        <w>спроможності</w>
        <pc>(</pc>
        <g/>
        <w>ПКС</w>
        <g/>
        <pc>)</pc>
        <w>в</w>
        <w>Україні</w>
        <w>був</w>
        <w>у</w>
        <w>3,98</w>
        <w>раза</w>
        <w>вищим</w>
        <pc>(</pc>
        <g/>
        <w>$</w>
        <g/>
        <w>7</w>
        <g/>
        <pc>,</pc>
        <g/>
        <w>96</w>
        <w>тис</w>
        <g/>
        <pc>.</pc>
        <g/>
        <pc>)</pc>
        <g/>
        <pc>,</pc>
        <w>аніж</w>
        <w>за</w>
        <w>номіналом</w>
        <pc>(</pc>
        <g/>
        <w>$</w>
        <g/>
        <w>2</w>
        <w>тис</w>
        <g/>
        <pc>.</pc>
        <g/>
        <pc>)</pc>
        <g/>
        <pc>.</pc>
        <w>У</w>
        <w>США</w>
        <w>вони</w>
        <w>ідентичні</w>
        <g/>
        <pc>,</pc>
        <w>отже</w>
        <g/>
        <pc>,</pc>
        <w>отримуємо</w>
        <w>коефіцієнт</w>
        <w>3</w>
        <g/>
        <pc>,</pc>
        <g/>
        <w>98</w>
        <g/>
        <pc>,</pc>
        <w>на</w>
        <w>який</w>
        <w>потрібно</w>
        <w>помножити</w>
        <w>середні</w>
        <w>доходи</w>
        <w>середнього</w>
        <w>класу</w>
        <w>в</w>
        <w>Україні</w>
        <g/>
        <pc>,</pc>
        <w>щоб</w>
        <w>отримати</w>
        <w>їх</w>
        <w>еквівалент</w>
        <w>у</w>
        <w>Сполучених</w>
        <w>Штатах</w>
        <g/>
        <pc>.</pc>
        <w>Якщо</w>
        <w>там</w>
        <w>вони</w>
        <w>стартували</w>
        <w>від</w>
        <w>$</w>
        <g/>
        <w>11</w>
        <g/>
        <pc>,</pc>
        <g/>
        <w>8</w>
        <w>тис</w>
        <g/>
        <pc>.</pc>
        <g/>
        <pc>/</pc>
        <g/>
        <w>рік</w>
        <w>на</w>
        <w>члена</w>
        <w>сім’ї</w>
        <g/>
        <pc>,</pc>
        <w>то</w>
        <w>в</w>
        <w>нас</w>
        <g/>
        <pc>,</pc>
        <w>коли</w>
        <w>перерахувати</w>
        <w>за</w>
        <w>коефіцієнтом</w>
        <w>3</w>
        <g/>
        <pc>,</pc>
        <g/>
        <w>98</w>
        <g/>
        <pc>,</pc>
        <w>згадані</w>
        <w>вище</w>
        <w>31</w>
        <g/>
        <pc>,</pc>
        <g/>
        <w>2</w>
        <g/>
        <w>%</w>
        <w>людей</w>
        <w>середнього</w>
        <w>доходу</w>
        <w>мали</w>
        <w>$</w>
        <g/>
        <w>5</w>
        <g/>
        <pc>,</pc>
        <g/>
        <w>8</w>
        <w>тис</w>
        <g/>
        <pc>.</pc>
        <w>за</w>
        <w>ПКС</w>
        <w>на</w>
        <w>рік</w>
        <w>і</w>
        <w>більше</w>
        <g/>
        <pc>.</pc>
        <w>Отже</w>
        <g/>
        <pc>,</pc>
        <w>питома</w>
        <w>вага</w>
        <w>українського</w>
        <w>середнього</w>
        <w>класу</w>
        <w>в</w>
        <w>структурі</w>
        <w>суспільства</w>
        <w>не</w>
        <w>лише</w>
        <w>майже</w>
        <w>удвічі</w>
        <w>менша</w>
        <w>за</w>
        <w>частку</w>
        <w>американського</w>
        <g/>
        <pc>,</pc>
        <w>він</w>
        <w>ще</w>
        <w>й</w>
        <w>має</w>
        <w>дещо</w>
        <w>нижчий</w>
        <w>рівень</w>
        <w>життя</w>
        <g/>
        <pc>.</pc>
        <w>Щоправда</w>
        <g/>
        <pc>,</pc>
        <w>не</w>
        <w>удвічі</w>
        <g/>
        <pc>,</pc>
        <w>адже</w>
        <w>порівняно</w>
        <w>зі</w>
        <w>США</w>
        <w>в</w>
        <w>нас</w>
        <w>набагато</w>
        <w>більші</w>
        <w>статистично</w>
        <w>необліковані</w>
        <w>доходи</w>
        <g/>
        <pc>.</pc>
      </p>
      <p>
        <w>Дещо</w>
        <w>краще</w>
        <w>співвідношення</w>
        <w>дає</w>
        <w>порівняння</w>
        <w>доходів</w>
        <w>за</w>
        <w>паритетом</w>
        <w>купівельної</w>
        <w>спроможності</w>
        <w>в</w>
        <w>людей</w>
        <w>середнього</w>
        <w>доходу</w>
        <w>в</w>
        <w>Україні</w>
        <w>та</w>
        <w>Німеччині</w>
        <g/>
        <pc>.</pc>
        <w>Там</w>
        <w>до</w>
        <w>них</w>
        <w>зараховують</w>
        <w>58</w>
        <g/>
        <w>%</w>
        <w>домогосподарств</w>
        <g/>
        <pc>,</pc>
        <w>які</w>
        <w>мають</w>
        <w>на</w>
        <w>члена</w>
        <w>сім’ї</w>
        <w>від</w>
        <w>€</w>
        <g/>
        <w>7</w>
        <g/>
        <pc>,</pc>
        <g/>
        <w>2</w>
        <w>тис</w>
        <g/>
        <pc>.</pc>
        <w>до</w>
        <w>€</w>
        <g/>
        <w>15</w>
        <g/>
        <pc>,</pc>
        <g/>
        <w>3</w>
        <w>тис</w>
        <g/>
        <pc>.</pc>
        <w>на</w>
        <w>рік</w>
        <g/>
        <pc>.</pc>
        <w>Коли</w>
        <w>взяти</w>
        <w>до</w>
        <w>уваги</w>
        <w>різницю</w>
        <w>ВВП</w>
        <w>на</w>
        <w>особу</w>
        <w>за</w>
        <w>номіналом</w>
        <w>та</w>
        <w>ПКС</w>
        <w>у</w>
        <w>наших</w>
        <w>країнах</w>
        <g/>
        <pc>,</pc>
        <w>яка</w>
        <w>дає</w>
        <w>коефіцієнт</w>
        <w>4</w>
        <g/>
        <pc>,</pc>
        <g/>
        <w>54</w>
        <g/>
        <pc>,</pc>
        <w>то</w>
        <w>згадані</w>
        <w>31</w>
        <g/>
        <pc>,</pc>
        <g/>
        <w>2</w>
        <g/>
        <w>%</w>
        <w>українських</w>
        <w>представників</w>
        <w>середнього</w>
        <w>класу</w>
        <w>мали</w>
        <w>2015</w>
        <w>року</w>
        <w>дохід</w>
        <w>від</w>
        <w>€</w>
        <g/>
        <w>5</w>
        <g/>
        <pc>,</pc>
        <g/>
        <w>9</w>
        <w>тис</w>
        <g/>
        <pc>.</pc>
        <g/>
        <pc>,</pc>
        <w>що</w>
        <w>майже</w>
        <w>зіставно</w>
        <w>з</w>
        <w>доходом</w>
        <w>середнього</w>
        <w>класу</w>
        <w>у</w>
        <w>ФРН</w>
        <g/>
        <pc>.</pc>
      </p>
      <gap/>
    </chunk>
    <chunk src="http://tyzhden.ua/Economics/191978">
      <gap/>
      <p>
        <w>Прогноз</w>
        <w>Міненерго</w>
        <w>щодо</w>
        <w>структури</w>
        <w>палива</w>
        <w>на</w>
        <w>травень</w>
        <w>передбачає</w>
        <w>виробництво</w>
        <w>на</w>
        <w>антрацитових</w>
        <w>блоках</w>
        <w>лише</w>
        <w>6</w>
        <g/>
        <w>%</w>
        <w>усього</w>
        <w>струму</w>
        <w>українських</w>
        <w>ТЕС</w>
        <pc>(</pc>
        <g/>
        <w>180</w>
        <w>млн</w>
        <w>кВт</w>
        <g/>
        <pc>•</pc>
        <g/>
        <w>год</w>
        <w>із</w>
        <w>2,97</w>
        <w>млрд</w>
        <w>кВт</w>
        <g/>
        <pc>•</pc>
        <g/>
        <w>год</w>
        <g/>
        <pc>)</pc>
        <g/>
        <pc>,</pc>
        <w>тоді</w>
        <w>як</w>
        <w>у</w>
        <w>минулі</w>
        <w>роки</w>
        <w>їхня</w>
        <w>частка</w>
        <w>сягала</w>
        <w>35</w>
        <g/>
        <pc>–</pc>
        <g/>
        <w>40</w>
        <g/>
        <w>%</w>
        <g/>
        <pc>.</pc>
        <w>Йдеться</w>
        <w>про</w>
        <w>генерацію</w>
        <w>на</w>
        <w>поки</w>
        <w>що</w>
        <w>ізольованій</w>
        <w>від</w>
        <w>решти</w>
        <w>країни</w>
        <w>Луганській</w>
        <w>ТЕС</w>
        <g/>
        <pc>,</pc>
        <w>яка</w>
        <w>в</w>
        <w>режимі</w>
        <w>енергоострова</w>
        <w>забезпечує</w>
        <w>підконтрольній</w>
        <w>Україні</w>
        <w>райони</w>
        <g/>
        <pc>.</pc>
        <w>Усе</w>
        <w>це</w>
        <w>в</w>
        <w>умовах</w>
        <g/>
        <pc>,</pc>
        <w>коли</w>
        <w>струму</w>
        <w>вистачає</w>
        <w>не</w>
        <w>тільки</w>
        <w>для</w>
        <w>внутрішнього</w>
        <w>ринку</w>
        <g/>
        <pc>,</pc>
        <w>а</w>
        <w>й</w>
        <w>для</w>
        <w>зовнішнього</w>
        <g/>
        <pc>,</pc>
        <w>коли</w>
        <w>динамічно</w>
        <w>зростає</w>
        <w>його</w>
        <w>експорт</w>
        <g/>
        <pc>.</pc>
        <w>Зокрема</w>
        <g/>
        <pc>,</pc>
        <w>згідно</w>
        <w>з</w>
        <w>прогнозним</w>
        <w>балансом</w>
        <w>виробництва</w>
        <w>струму</w>
        <w>в</w>
        <w>травні</w>
        <w>Міненерго</w>
        <w>очікує</w>
        <w>збільшення</w>
        <w>постачання</w>
        <w>майже</w>
        <w>удвічі</w>
        <w>порівняно</w>
        <w>з</w>
        <w>травнем</w>
        <w>2016-го</w>
        <pc>(</pc>
        <g/>
        <w>до</w>
        <w>583</w>
        <w>млн</w>
        <w>кВт</w>
        <g/>
        <pc>•</pc>
        <g/>
        <w>год</w>
        <g/>
        <pc>)</pc>
        <w>за</w>
        <w>рахунок</w>
        <w>активних</w>
        <w>поставок</w>
        <w>до</w>
        <w>Молдови</w>
        <pc>(</pc>
        <g/>
        <w>до</w>
        <w>272</w>
        <w>млн</w>
        <w>кВт</w>
        <g/>
        <pc>•</pc>
        <g/>
        <w>год</w>
        <g/>
        <pc>)</pc>
        <g/>
        <pc>.</pc>
        <w>Ще</w>
        <w>раз</w>
        <w>наголосимо</w>
        <g/>
        <pc>:</pc>
        <w>усе</w>
        <w>це</w>
        <w>без</w>
        <w>відновлення</w>
        <w>роботи</w>
        <w>антрацитових</w>
        <w>блоків</w>
        <w>ТЕС</w>
        <g/>
        <pc>.</pc>
      </p>
      <gap/>
    </chunk>
    <chunk src="http://tyzhden.ua/PrivateUrbanStudies/192952">
      <gap/>
      <p>
        <w>Черкаси</w>
        <pc>—</pc>
        <w>це</w>
        <w>місто</w>
        <g/>
        <pc>,</pc>
        <w>де</w>
        <w>немає</w>
        <w>бетонних</w>
        <w>джунглів</w>
        <g/>
        <pc>,</pc>
        <w>стовпів</w>
        <w>пилу</w>
        <w>та</w>
        <w>поодиноких</w>
        <w>берізок</w>
        <w>край</w>
        <w>дороги</w>
        <g/>
        <pc>.</pc>
        <w>Фантастично</w>
        <w>красиво</w>
        <w>стає</w>
        <w>після</w>
        <w>зими</w>
        <pc>—</pc>
        <w>у</w>
        <w>квітні</w>
        <g/>
        <pc>-</pc>
        <g/>
        <w>травні</w>
        <g/>
        <pc>,</pc>
        <w>коли</w>
        <w>на</w>
        <w>кожній</w>
        <w>вуличці</w>
        <w>розцвітають</w>
        <w>вишні</w>
        <g/>
        <pc>,</pc>
        <w>яблуні</w>
        <g/>
        <pc>,</pc>
        <w>абрикоси</w>
        <g/>
        <pc>,</pc>
        <w>бузок</w>
        <g/>
        <pc>.</pc>
        <w>А</w>
        <w>довкола</w>
        <w>розпускаються</w>
        <w>каштани</w>
        <g/>
        <pc>.</pc>
        <w>Цей</w>
        <w>зелений</w>
        <w>рай</w>
        <w>триває</w>
        <w>майже</w>
        <w>до</w>
        <w>листопада</w>
        <g/>
        <pc>.</pc>
      </p>
      <p>
        <w>Черкаси</w>
        <w>поділені</w>
        <w>на</w>
        <w>квадрати</w>
        <w>й</w>
        <w>відстань</w>
        <w>від</w>
        <w>пункту</w>
        <w>А</w>
        <w>до</w>
        <w>пункту</w>
        <w>Б</w>
        <w>тут</w>
        <w>вимірюється</w>
        <w>кварталами</w>
        <g/>
        <pc>.</pc>
        <w>Спочатку</w>
        <w>я</w>
        <w>наївно</w>
        <w>думала</w>
        <g/>
        <pc>,</pc>
        <w>що</w>
        <g/>
        <pc>,</pc>
        <w>якщо</w>
        <w>побачила</w>
        <w>назву</w>
        <w>вулиці</w>
        <g/>
        <pc>,</pc>
        <w>яку</w>
        <w>знаю</w>
        <g/>
        <pc>,</pc>
        <w>то</w>
        <w>точно</w>
        <w>її</w>
        <w>знайду</w>
        <g/>
        <pc>.</pc>
        <w>Як</w>
        <w>же</w>
        <w>була</w>
        <w>здивована</w>
        <g/>
        <pc>,</pc>
        <w>коли</w>
        <w>стало</w>
        <w>ясно</w>
        <g/>
        <pc>,</pc>
        <w>що</w>
        <w>більш</w>
        <w>ніж</w>
        <w>половина</w>
        <w>вулиць</w>
        <w>починається</w>
        <w>на</w>
        <w>одному</w>
        <w>кінці</w>
        <w>міста</w>
        <w>й</w>
        <w>закінчується</w>
        <w>на</w>
        <w>іншому</w>
        <g/>
        <pc>.</pc>
        <w>Черкаси</w>
        <pc>—</pc>
        <w>це</w>
        <w>шахова</w>
        <w>дошка</w>
        <w>довгих</w>
        <w>паралельних</w>
        <w>вулиць</w>
        <g/>
        <pc>.</pc>
        <w>А</w>
        <w>через</w>
        <w>центр</w>
        <w>пролягає</w>
        <w>головний</w>
        <w>бульвар</w>
        <w>міста</w>
        <pc>—</pc>
        <w>бульвар</w>
        <w>Шевченка</w>
        <g/>
        <pc>,</pc>
        <w>рясно</w>
        <w>висаджений</w>
        <w>каштанами</w>
        <w>та</w>
        <w>вкладений</w>
        <w>плиткою</w>
        <g/>
        <pc>.</pc>
      </p>
      <p>
        <w>У</w>
        <w>місті</w>
        <w>немає</w>
        <w>якогось</w>
        <w>визначеного</w>
        <w>стилю</w>
        <w>будинків</w>
        <g/>
        <pc>.</pc>
        <w>У</w>
        <w>центрі</w>
        <w>можна</w>
        <w>побачити</w>
        <w>багатоповерхівки</w>
        <g/>
        <pc>,</pc>
        <w>а</w>
        <w>на</w>
        <w>сусідній</w>
        <w>вулиці</w>
        <pc>—</pc>
        <w>приватні</w>
        <w>будинки</w>
        <w>з</w>
        <w>садами</w>
        <g/>
        <pc>.</pc>
      </p>
      <p>
        <w>Біля</w>
        <w>водосховища</w>
        <pc>-</pc>
        <w>соснові</w>
        <w>ліси</w>
        <g/>
        <pc>.</pc>
        <w>Могутні</w>
        <g/>
        <pc>,</pc>
        <w>старі</w>
        <g/>
        <pc>,</pc>
        <w>аж</w>
        <w>пашіють</w>
        <w>енергією</w>
        <g/>
        <pc>.</pc>
        <w>Першим</w>
        <w>я</w>
        <w>побачила</w>
        <w>парк</w>
        <pc>"</pc>
        <g/>
        <w>Сосновий</w>
        <w>Бір</w>
        <g/>
        <pc>"</pc>
        <w>на</w>
        <w>території</w>
        <w>міста</w>
        <g/>
        <pc>,</pc>
        <w>який</w>
        <w>має</w>
        <w>250</w>
        <w>га</w>
        <w>площі</w>
        <g/>
        <pc>.</pc>
        <w>В</w>
        <w>парку</w>
        <w>є</w>
        <w>розваги</w>
        <w>на</w>
        <w>будь-який</w>
        <w>смак</w>
        <g/>
        <pc>,</pc>
        <w>дитячі</w>
        <w>майданчики</w>
        <g/>
        <pc>,</pc>
        <w>лавочки</w>
        <w>з</w>
        <w>видом</w>
        <w>на</w>
        <w>водосховище</w>
        <g/>
        <pc>,</pc>
        <w>арковий</w>
        <pc>“</pc>
        <g/>
        <w>місток</w>
        <w>кохання</w>
        <g/>
        <pc>”</pc>
        <g/>
        <pc>,</pc>
        <w>виставки</w>
        <w>з</w>
        <w>каменю</w>
        <w>та</w>
        <w>дерева</w>
        <g/>
        <pc>.</pc>
        <w>Неподалік</w>
        <pc>—</pc>
        <w>пляж</w>
        <g/>
        <pc>.</pc>
        <w>Люблю</w>
        <w>цей</w>
        <w>парк</w>
        <g/>
        <pc>,</pc>
        <w>особливо</w>
        <w>влітку</w>
        <g/>
        <pc>,</pc>
        <w>адже</w>
        <w>він</w>
        <w>ховає</w>
        <w>від</w>
        <w>безжальної</w>
        <w>спеки</w>
        <w>поміж</w>
        <w>соснами</w>
        <w>і</w>
        <w>дозволяє</w>
        <w>насолоджуватися</w>
        <w>сонечком</w>
        <g/>
        <pc>.</pc>
      </p>
      <gap/>
      <p>
        <w>Для</w>
        <w>вечірніх</w>
        <w>прогулянок</w>
        <w>найбільше</w>
        <w>полюбляю</w>
        <w>парк</w>
        <pc>"</pc>
        <g/>
        <w>Долина</w>
        <w>Троянд</w>
        <g/>
        <pc>"</pc>
        <w>неподалік</w>
        <w>від</w>
        <w>центру</w>
        <w>на</w>
        <w>березі</w>
        <w>Кременчуцького</w>
        <w>водосховища</w>
        <g/>
        <pc>.</pc>
        <w>В</w>
        <w>парку</w>
        <w>відбуваються</w>
        <w>концерти</w>
        <g/>
        <pc>,</pc>
        <w>фестиваль</w>
        <w>короткометражок</w>
        <pc>"</pc>
        <g/>
        <w>КіноШот</w>
        <g/>
        <pc>"</pc>
        <g/>
        <pc>,</pc>
        <w>також</w>
        <w>є</w>
        <pc>"</pc>
        <g/>
        <w correct="рив’єра">ривьєра</w>
        <g/>
        <pc>"</pc>
        <w>і</w>
        <w>парк</w>
        <w>розваг</w>
        <g/>
        <pc>.</pc>
        <w>Від</w>
        <w>спеки</w>
        <w>рятують</w>
        <pc>“</pc>
        <g/>
        <w>танцюючі</w>
        <g/>
        <pc>”</pc>
        <w>кольорові</w>
        <w>фонтани</w>
        <g/>
        <pc>,</pc>
        <w>які</w>
        <w>особливо</w>
        <w>полюбляє</w>
        <w>малеча</w>
        <g/>
        <pc>.</pc>
      </p>
      <gap/>
    </chunk>
    <chunk src="http://tyzhden.ua/PrivateUrbanStudies/192301">
      <gap/>
      <p>
        <w>Коли</w>
        <w>згадаю</w>
        <w>про</w>
        <w>історико-архітектурний</w>
        <w>спадок</w>
        <pc>—</pc>
        <w>найстаріший</w>
        <w>християнський</w>
        <w>храм</w>
        <w>України</w>
        <w>та</w>
        <w>всієї</w>
        <w>Східної</w>
        <w>Європи</w>
        <g/>
        <pc>,</pc>
        <w>що</w>
        <w>вцілів</w>
        <w>до</w>
        <w>нашого</w>
        <w>часу</w>
        <g/>
        <pc>,</pc>
        <w>найбільшу</w>
        <w>в</w>
        <w>Європі</w>
        <w>фортецю</w>
        <w>ХVIII</w>
        <g/>
        <pc>-</pc>
        <g/>
        <w>XIX</w>
        <w>ст</w>
        <g/>
        <pc>.</pc>
        <g/>
        <pc>,</pc>
        <w>найвідоміший</w>
        <w>православний</w>
        <w>монастир</w>
        <w>на</w>
        <w>східнослов’янських</w>
        <w>землях</w>
        <g/>
        <pc>,</pc>
        <w>найбільший</w>
        <w>у</w>
        <w>Європі</w>
        <w>скансен</w>
        <w>та</w>
        <w>багато</w>
        <w>іншого</w>
        <pc>–</pc>
        <w>ви</w>
        <w>теж</w>
        <w>відповісте</w>
        <g/>
        <pc>:</pc>
        <pc>«</pc>
        <g/>
        <w>це</w>
        <w>все</w>
        <w>вікіпедійна</w>
        <w>інформація</w>
        <g/>
        <pc>»</pc>
        <g/>
        <pc>.</pc>
      </p>
      <gap/>
    </chunk>
    <chunk src="http://tyzhden.ua/Culture/191961">
      <gap/>
      <p>
        <w>Дослідження</w>
        <w>складових</w>
        <w>ґрунту</w>
        <w>спочатку</w>
        <w>принесло</w>
        <w>нове</w>
        <w>розчарування</w>
        <g/>
        <pc>:</pc>
        <w>по</w>
        <w>всій</w>
        <w>поверхні</w>
        <pc>«</pc>
        <g/>
        <w>хворих</w>
        <g/>
        <pc>»</pc>
        <w>стулок</w>
        <w>були</w>
        <w>виявлені</w>
        <w>цинкові</w>
        <w>білила</w>
        <g/>
        <pc>,</pc>
        <w>які</w>
        <w>в</w>
        <w>живописі</w>
        <w>почали</w>
        <w>використовувати</w>
        <w>в</w>
        <w>XIX</w>
        <w>столітті</w>
        <w>замість</w>
        <w>традиційних</w>
        <w>свинцевих</w>
        <g/>
        <pc>.</pc>
        <w>Але</w>
        <w>знову</w>
        <w>ж</w>
        <w>таки</w>
        <w>на</w>
        <w>правій</w>
        <w>стулці</w>
        <w>жодних</w>
        <w>цинкових</w>
        <w>білил</w>
        <g/>
        <pc>!</pc>
        <w>До</w>
        <w>того</w>
        <w>ж</w>
        <g/>
        <pc>,</pc>
        <w>за</w>
        <w>висновками</w>
        <w>наших</w>
        <w>партнерів</w>
        <g/>
        <pc>-</pc>
        <g/>
        <w>хіміків</w>
        <w>із</w>
        <w>Національного</w>
        <w>науково</w>
        <g/>
        <pc>-</pc>
        <g/>
        <w>дослідного</w>
        <w>реставраційного</w>
        <w>центру</w>
        <w>України</w>
        <w>та</w>
        <w>бюро</w>
        <w>технічної</w>
        <w>експертизи</w>
        <pc>«</pc>
        <g/>
        <w>Артлаб</w>
        <g/>
        <pc>»</pc>
        <g/>
        <pc>,</pc>
        <w>пігменти</w>
        <g/>
        <pc>,</pc>
        <w>застосовані</w>
        <w>у</w>
        <w>фарбах</w>
        <g/>
        <pc>,</pc>
        <w>на</w>
        <w>всіх</w>
        <w>трьох</w>
        <w>частинах</w>
        <pc>«</pc>
        <g/>
        <w>Спокуси</w>
        <w>св</w>
        <g/>
        <pc>.</pc>
        <w>Антонія</w>
        <g/>
        <pc>»</pc>
        <w>виявилися</w>
        <w>автентичними</w>
        <g/>
        <pc>:</pc>
        <w>кістяна</w>
        <w>чорна</w>
        <g/>
        <pc>,</pc>
        <w>азурит</w>
        <g/>
        <pc>,</pc>
        <w>натуральний</w>
        <w>ультрамарин</w>
        <g/>
        <pc>,</pc>
        <w>малахіт</w>
        <w>і</w>
        <w>кіновар</w>
        <pc>—</pc>
        <w>той</w>
        <w>самий</w>
        <w>обмежений</w>
        <w>репертуар</w>
        <g/>
        <pc>,</pc>
        <w>що</w>
        <w>був</w>
        <w>доступний</w>
        <w>живописцям</w>
        <w>XV</w>
        <g/>
        <pc>–</pc>
        <g/>
        <w>XVI</w>
        <w>століття</w>
        <g/>
        <pc>,</pc>
        <w>зокрема</w>
        <w>Ієронімусові</w>
        <w>Босху</w>
        <w>та</w>
        <w>його</w>
        <w>помічникам</w>
        <g/>
        <pc>.</pc>
      </p>
      <gap/>
      <p>
        <w>Насамкінець</w>
        <w>маю</w>
        <w>сказати</w>
        <g/>
        <pc>,</pc>
        <w>що</w>
        <w>триптих</w>
        <w>із</w>
        <w>босхівської</w>
        <w>майстерні</w>
        <w>справді</w>
        <w>є</w>
        <w>лише</w>
        <w>однією</w>
        <w>із</w>
        <w>загадкових</w>
        <pc>«</pc>
        <g/>
        <w>копій</w>
        <g/>
        <pc>»</pc>
        <w>в</w>
        <w>експозиції</w>
        <w>Музею</w>
        <w>Ханенків</w>
        <g/>
        <pc>.</pc>
        <w>Маємо</w>
        <g/>
        <pc>,</pc>
        <w>приміром</w>
        <g/>
        <pc>,</pc>
        <w>іще</w>
        <w>версію</w>
        <pc>«</pc>
        <g/>
        <w>Старого</w>
        <w>у</w>
        <w>східному</w>
        <w>вбранні</w>
        <g/>
        <pc>»</pc>
        <g/>
        <pc>.</pc>
        <w>Оригінал</w>
        <w>цього</w>
        <w>шедевра</w>
        <w>Рембрандта</w>
        <g/>
        <pc>,</pc>
        <w>як</w>
        <w>відомо</w>
        <g/>
        <pc>,</pc>
        <w>належить</w>
        <w>нью-йоркському</w>
        <w>Музею</w>
        <w>мистецтва</w>
        <pc>«</pc>
        <g/>
        <w>Метрополітен</w>
        <g/>
        <pc>»</pc>
        <g/>
        <pc>.</pc>
        <w>Ханенківську</w>
        <w>версію</w>
        <w>портрета</w>
        <w>підписано</w>
        <g/>
        <pc>,</pc>
        <w>і</w>
        <w>підпис</w>
        <w>цей</w>
        <w>є</w>
        <w>автентичним</w>
        <g/>
        <pc>.</pc>
        <w>Чому</w>
        <w>так</w>
        <w>і</w>
        <w>яка</w>
        <w>традиція</w>
        <w>європейського</w>
        <w>малярства</w>
        <w>за</w>
        <w>цим</w>
        <w>криється</w>
        <pc>—</pc>
        <w>предмет</w>
        <w>іншого</w>
        <w>дослідження</w>
        <g/>
        <pc>,</pc>
        <w>а</w>
        <w>також</w>
        <w>іншої</w>
        <g/>
        <pc>,</pc>
        <w>не</w>
        <w>менш</w>
        <w>тривалої</w>
        <w>розмови</w>
        <g/>
        <pc>,</pc>
        <w>на</w>
        <w>яку</w>
        <w>зважиться</w>
        <w>лише</w>
        <w>той</w>
        <g/>
        <pc>,</pc>
        <w>хто</w>
        <w>справді</w>
        <w>хоче</w>
        <w>бути</w>
        <g/>
        <pc>,</pc>
        <w>а</w>
        <w>не</w>
        <w>здаватися</w>
        <w>знавцем</w>
        <w>старовинного</w>
        <w>живопису</w>
        <g/>
        <pc>.</pc>
      </p>
      <gap/>
    </chunk>
    <chunk src="http://tyzhden.ua/PressReleases/192582">
      <gap/>
      <p>
        <w>15</w>
        <w>липня</w>
        <w>2017</w>
        <w>року</w>
        <w>у</w>
        <w>Київському</w>
        <w>гольф</w>
        <w>клубі</w>
        <w>"GolfStream"</w>
        <w>компанія</w>
        <w>АВТ</w>
        <w>Баварія</w>
        <w>Україна</w>
        <g/>
        <pc>,</pc>
        <w>офіційний</w>
        <w>імпортер</w>
        <w>BMW</w>
        <w>в</w>
        <w>Україні</w>
        <g/>
        <pc>,</pc>
        <w>проведе</w>
        <w>національний</w>
        <w>відбірковий</w>
        <w>етап</w>
        <w>одного</w>
        <w>з</w>
        <w>найпрестижніших</w>
        <w>турнірів</w>
        <w>у</w>
        <w>світовому</w>
        <w>гольфі</w>
        <w>серед</w>
        <w>спортсменів</w>
        <g/>
        <pc>-</pc>
        <g/>
        <w>аматорів</w>
        <pc>-</pc>
        <w>BMW</w>
        <w>Golf</w>
        <w>Cup</w>
        <w>International</w>
        <w>2017</w>
        <g/>
        <pc>.</pc>
        <w>Турнір</w>
        <w>розрахований</w>
        <w>на</w>
        <w>72</w>
        <w>учасника</w>
        <g/>
        <pc>,</pc>
        <w>переможці</w>
        <w>якого</w>
        <w>отримають</w>
        <w>почесне</w>
        <w>право</w>
        <w>представляти</w>
        <w>Україну</w>
        <w>на</w>
        <w>міжнародному</w>
        <w>фіналі</w>
        <w>в</w>
        <w>Південно</w>
        <g/>
        <pc>-</pc>
        <g/>
        <w>Африканській</w>
        <w>Республіці</w>
        <g/>
        <pc>.</pc>
      </p>
      <gap/>
    </chunk>
    <chunk src="http://tyzhden.ua/PressReleases/192675">
      <gap/>
      <p>
        <w>Toyota</w>
        <w>в</w>
        <w>рамках</w>
        <w>програми</w>
        <w>знайомства</w>
        <w>української</w>
        <w>аудиторії</w>
        <w>з</w>
        <w>гібридними</w>
        <w>технологіями</w>
        <w>представила</w>
        <w>креативну</w>
        <w>експозицію</w>
        <w>на</w>
        <w>Фестивалі</w>
        <w>вуличної</w>
        <w>їжі</w>
        <g/>
        <pc>,</pc>
        <w>який</w>
        <w>проходить</w>
        <w>у</w>
        <w>Києві</w>
        <g/>
        <pc>.</pc>
        <w>Один</w>
        <w>із</w>
        <w>найпопулярніших</w>
        <w>культурних</w>
        <w>заходів</w>
        <w>світового</w>
        <w>рівня</w>
        <w>відбувся</w>
        <w>на</w>
        <w>арт</w>
        <g/>
        <pc>-</pc>
        <g/>
        <w>заводі</w>
        <pc>«</pc>
        <g/>
        <w>Платформа</w>
        <g/>
        <pc>»</pc>
        <w>13</w>
        <g/>
        <pc>-</pc>
        <g/>
        <w>14</w>
        <w>травня</w>
        <g/>
        <pc>,</pc>
        <w>вже</w>
        <w>вдруге</w>
        <w>у</w>
        <w>2017</w>
        <w>році</w>
        <g/>
        <pc>.</pc>
        <w>Сотні</w>
        <w>молодих</w>
        <w>та</w>
        <w>активних</w>
        <w>киян</w>
        <w>і</w>
        <w>гостей</w>
        <w>міста</w>
        <w>змогли</w>
        <w>познайомитися</w>
        <w>з</w>
        <w>гібридними</w>
        <w>кросоверами</w>
        <w>Toyota</w>
        <w>RAV4</w>
        <g/>
        <pc>,</pc>
        <w>записатися</w>
        <w>на</w>
        <w>тест</w>
        <g/>
        <pc>-</pc>
        <g/>
        <w>драйв</w>
        <g/>
        <pc>,</pc>
        <w>отримати</w>
        <w>яскраві</w>
        <w>сюрпризи</w>
        <w>та</w>
        <w>навіть</w>
        <w>продегустувати</w>
        <w>попкорн</w>
        <g/>
        <pc>,</pc>
        <w>приготований</w>
        <w>за</w>
        <w>допомогою</w>
        <w>рідкого</w>
        <w>азоту</w>
        <pc>–</pc>
        <w>такий</w>
        <w>собі</w>
        <w>гібрид</w>
        <w>у</w>
        <w>гастрономії</w>
        <w>для</w>
        <w>гостей</w>
        <w>стенда</w>
        <w>Toyota</w>
        <g/>
        <pc>!</pc>
      </p>
      <gap/>
    </chunk>
    <chunk src="http://tyzhden.ua/PressReleases/191162">
      <gap/>
      <p>
        <w>Група</w>
        <w>компаній</w>
        <pc>«</pc>
        <g/>
        <w>Ензим</w>
        <g/>
        <pc>»</pc>
        <pc>—</pc>
        <w>це</w>
        <w>єдине</w>
        <w>в</w>
        <w>Україні</w>
        <w>велике</w>
        <w>промислове</w>
        <w>підприємство</w>
        <w>з</w>
        <w>виробництва</w>
        <w>біотехнологічної</w>
        <w>продукції</w>
        <w>за</w>
        <w>допомогою</w>
        <w>мікробного</w>
        <w>синтезу</w>
        <g/>
        <pc>.</pc>
        <w>Завод</w>
        <pc>«</pc>
        <g/>
        <w>Ензим</w>
        <g/>
        <pc>»</pc>
        <w>працює</w>
        <w>з</w>
        <w>січня</w>
        <w>1971</w>
        <w>р</w>
        <w>СРСР</w>
        <pc>«</pc>
        <g/>
        <w>Ензим</w>
        <g/>
        <pc>»</pc>
        <w>найбільшим</w>
        <w>виробником</w>
        <w>ферментних</w>
        <w>препаратів</w>
        <g/>
        <pc>.</pc>
      </p>
      <gap/>
    </chunk>
    <chunk src="">
      <gap/>
      <p>
        <w>Повідомляємо</w>
        <g/>
        <pc>,</pc>
        <w>що</w>
        <w>22</w>
        <w>травня</w>
        <w>2017</w>
        <w>року</w>
        <w>Мережа</w>
        <w>Ланет</w>
        <w>заблокує</w>
        <w>доступ</w>
        <w>до</w>
        <w>заборонених</w>
        <w>сервісів</w>
        <g/>
        <pc>.</pc>
      </p>
      <gap/>
    </chunk>
    <chunk src="http://tyzhden.ua/Auto/181472">
      <gap/>
      <p>
        <w>Ви</w>
        <w>казали</w>
        <w>про</w>
        <w>1,2</w>
        <w>тис</w>
        <g/>
        <pc>.</pc>
        <w>проданих</w>
        <w>електричних</w>
        <w>авто</w>
        <g/>
        <pc>.</pc>
        <w>Якщо</w>
        <w>рахувати</w>
        <w>від</w>
        <w>загального</w>
        <w>ринку</w>
        <w>проданих</w>
        <w>авто</w>
        <w>в</w>
        <w>Україні</w>
        <g/>
        <pc>,</pc>
        <w>то</w>
        <w>яка</w>
        <w>це</w>
        <w>частка</w>
        <g/>
        <pc>?</pc>
      </p>
      <p>
        <pc>—</pc>
        <w>Припустімо</w>
        <g/>
        <pc>,</pc>
        <w>що</w>
        <w>ми</w>
        <w>завершимо</w>
        <w>рік</w>
        <w>навіть</w>
        <w>із</w>
        <w>показником</w>
        <w>1,2</w>
        <w>тис</w>
        <g/>
        <pc>.</pc>
        <g/>
        <pc>,</pc>
        <w>а</w>
        <w>загальний</w>
        <w>ринок</w>
        <w>продажу</w>
        <w>авто</w>
        <w>в</w>
        <w>Україні</w>
        <w>2016-го</w>
        <g/>
        <pc>,</pc>
        <w>на</w>
        <w>мою</w>
        <w>думку</w>
        <g/>
        <pc>,</pc>
        <w>становитиме</w>
        <w>63</w>
        <w>тис</w>
        <g/>
        <pc>.</pc>
        <w>Тобто</w>
        <w>2</w>
        <g/>
        <w>%</w>
        <g/>
        <pc>.</pc>
        <w>У</w>
        <w>2015-му</w>
        <w>продали</w>
        <w>400</w>
        <w>електрокарів</w>
        <w>і</w>
        <w>це</w>
        <w>становило</w>
        <w>0</w>
        <g/>
        <pc>,</pc>
        <g/>
        <w>8</w>
        <g/>
        <w>%</w>
        <g/>
        <pc>.</pc>
        <w>Тобто</w>
        <w>все</w>
        <w>одно</w>
        <w>частка</w>
        <w>зростає</w>
        <g/>
        <pc>.</pc>
        <w>Якщо</w>
        <w>врахувати</w>
        <w>динаміку</w>
        <g/>
        <pc>,</pc>
        <w>вийдемо</w>
        <w>на</w>
        <w>4</w>
        <g/>
        <pc>–</pc>
        <g/>
        <w>5</w>
        <g/>
        <w>%</w>
        <pc>(</pc>
        <g/>
        <w>наступного</w>
        <w>року</w>
        <g/>
        <pc>.</pc>
        <pc>—</pc>
        <w>Ред</w>
        <g/>
        <pc>.</pc>
        <g/>
        <pc>)</pc>
        <g/>
        <pc>.</pc>
        <w>На</w>
        <w>мою</w>
        <w>думку</w>
        <g/>
        <pc>,</pc>
        <w>абсолютно</w>
        <w>непоганий</w>
        <w>показник</w>
        <g/>
        <pc>.</pc>
        <w>Лідери</w>
        <w>індустрії</w>
        <pc>—</pc>
        <w>країни</w>
        <w>Скандинавії</w>
        <pc>—</pc>
        <w>зараз</w>
        <w>продають</w>
        <w>15</w>
        <g/>
        <w>%</w>
        <g/>
        <pc>.</pc>
        <w>І</w>
        <w>вважають</w>
        <w>це</w>
        <w>чудовим</w>
        <w>показником</w>
        <g/>
        <pc>.</pc>
        <w>При</w>
        <w>тому</w>
        <w>що</w>
        <w>в</w>
        <w>нас</w>
        <w>немає</w>
        <w>надзвичайних</w>
        <w>норм</w>
        <pc>(</pc>
        <g/>
        <w>стимулювання</w>
        <g/>
        <pc>.</pc>
        <pc>—</pc>
        <w>Ред</w>
        <g/>
        <pc>.</pc>
        <g/>
        <pc>)</pc>
        <w>від</w>
        <w>держави</w>
        <g/>
        <pc>.</pc>
        <w>Зараз</w>
        <w>є</w>
        <w>цікавий</w>
        <w>законопроект</w>
        <w>про</w>
        <w>скасування</w>
        <w>ПДВ</w>
        <w>на</w>
        <w>багато</w>
        <w>груп</w>
        <w>товарів</w>
        <g/>
        <pc>,</pc>
        <w>зокрема</w>
        <w>й</w>
        <w>автомобілі</w>
        <pc>(</pc>
        <g/>
        <w>є</w>
        <w>відповідний</w>
        <w>законопроект</w>
        <w>№</w>
        <w>5494</w>
        <w>від</w>
        <w>06</w>
        <g/>
        <pc>.</pc>
        <g/>
        <w>12</w>
        <g/>
        <pc>.</pc>
        <g/>
        <w>2016</w>
        <w>року</w>
        <g/>
        <pc>.</pc>
        <pc>—</pc>
        <w>Ред</w>
        <g/>
        <pc>.</pc>
        <g/>
        <pc>)</pc>
        <g/>
        <pc>.</pc>
        <w>ПДВ</w>
        <pc>—</pc>
        <w>це</w>
        <w>головне</w>
        <w>надходження</w>
        <w>для</w>
        <w>держави</w>
        <g/>
        <pc>,</pc>
        <w>податок</w>
        <w>на</w>
        <w>прибуток</w>
        <w>мало</w>
        <w>хто</w>
        <w>сплачує</w>
        <g/>
        <pc>,</pc>
        <w>а</w>
        <w>якщо</w>
        <w>й</w>
        <w>сплачує</w>
        <g/>
        <pc>,</pc>
        <w>то</w>
        <w>він</w>
        <w>невеликий</w>
        <g/>
        <pc>.</pc>
        <w>Тому</w>
        <w>не</w>
        <w>думаю</w>
        <g/>
        <pc>,</pc>
        <w>що</w>
        <w>держава</w>
        <w>від</w>
        <w>цього</w>
        <w>відмовиться</w>
        <g/>
        <pc>.</pc>
        <w>Але</w>
        <w>законопроект</w>
        <w>про</w>
        <w>скасування</w>
        <w>ПДВ</w>
        <w>дуже</w>
        <w>цікавий</w>
        <g/>
        <pc>,</pc>
        <w>адже</w>
        <w>в</w>
        <w>проекті</w>
        <w>він</w>
        <w>стосується</w>
        <w>не</w>
        <w>лише</w>
        <w>автомобілів</w>
        <g/>
        <pc>.</pc>
        <w>Туди</w>
        <w>входять</w>
        <w>усі</w>
        <w>комплектуючі</w>
        <g/>
        <pc>,</pc>
        <w>послуги</w>
        <w>таксі</w>
        <w>та</w>
        <w>кур’єрських</w>
        <w>служб</w>
        <g/>
        <pc>,</pc>
        <w>які</w>
        <w>користуватимуться</w>
        <w>електрокарами</w>
        <g/>
        <pc>.</pc>
        <w>Тобто</w>
        <w>йдеться</w>
        <w>про</w>
        <w>всі</w>
        <w>сфери</w>
        <g/>
        <pc>,</pc>
        <w>де</w>
        <w>використовують</w>
        <w>електромобілі</w>
        <g/>
        <pc>.</pc>
        <w>Держава</w>
        <w>таким</w>
        <w>чином</w>
        <w>може</w>
        <w>створити</w>
        <w>абсолютно</w>
        <w>нову</w>
        <w>нішу</w>
        <g/>
        <pc>,</pc>
        <w>і</w>
        <w>я</w>
        <w>впевнений</w>
        <g/>
        <pc>,</pc>
        <w>що</w>
        <w>багато</w>
        <w>хто</w>
        <w>захоче</w>
        <w>туди</w>
        <w>увійти</w>
        <g/>
        <pc>.</pc>
        <w>Окрім</w>
        <w>екології</w>
        <w>це</w>
        <w>тягне</w>
        <w>за</w>
        <w>собою</w>
        <w>й</w>
        <w>інфраструктурні</w>
        <w>проекти</w>
        <g/>
        <pc>,</pc>
        <w>приватні</w>
        <w>інвестиції</w>
        <g/>
        <pc>,</pc>
        <w>що</w>
        <w>може</w>
        <w>стати</w>
        <w>певним</w>
        <w>локомотивом</w>
        <g/>
        <pc>.</pc>
      </p>
      <gap/>
    </chunk>
    <chunk src="http://tabloid.pravda.com.ua/lounge/5922834282ba9/">
      <gap/>
      <p>
        <pc>"</pc>
        <g/>
        <w>Народити</w>
        <w>в</w>
        <w>дев'ятнадцять</w>
        <w>років</w>
        <w>і</w>
        <w>в</w>
        <w>тридцять</w>
        <w>три</w>
        <w>роки</w>
        <pc>-</pc>
        <w>це</w>
        <w>абсолютно</w>
        <w>різний</w>
        <w>досвід</w>
        <g/>
        <pc>"</pc>
        <g/>
        <pc>,</pc>
        <pc>-</pc>
        <w>зауважила</w>
        <w>Осадча</w>
        <w>в</w>
        <w>інтерв’ю</w>
        <w>виданню</w>
        <g/>
        <pc>.</pc>
      </p>
      <p>
        <pc>"</pc>
        <g/>
        <w>У</w>
        <w>дев'ятнадцять</w>
        <w>ти</w>
        <w>боїшся</w>
        <g/>
        <pc>,</pc>
        <w>що</w>
        <w>життя</w>
        <w>проходить</w>
        <w>повз</w>
        <g/>
        <pc>,</pc>
        <w>поки</w>
        <w>ти</w>
        <w>вдома</w>
        <g/>
        <pc>.</pc>
        <w>У</w>
        <w>такому</w>
        <w>віці</w>
        <w>здається</w>
        <g/>
        <pc>,</pc>
        <w>що</w>
        <w>діти</w>
        <w>забирають</w>
        <w>час</w>
        <w>від</w>
        <w>чогось</w>
        <w>важливого</w>
        <g/>
        <pc>.</pc>
        <w>Але</w>
        <w>після</w>
        <w>тридцяти</w>
        <w>ти</w>
        <w>вже</w>
        <w>знаєш</w>
        <g/>
        <pc>,</pc>
        <w>що</w>
        <w>діти</w>
        <w>нічого</w>
        <w>не</w>
        <w>забирають</w>
        <g/>
        <pc>,</pc>
        <w>а</w>
        <w>тільки</w>
        <w>додають</w>
        <w>фарб</w>
        <w>у</w>
        <w>твоє</w>
        <w>життя</w>
        <g/>
        <pc>.</pc>
        <w>Вони</w>
        <w>ростуть</w>
        <w>настільки</w>
        <w>швидко</w>
        <g/>
        <pc>,</pc>
        <w>що</w>
        <w>потрібно</w>
        <w>ловити</w>
        <w>кожен</w>
        <w>момент</w>
        <g/>
        <pc>.</pc>
        <w>І</w>
        <w>встигнути</w>
        <w>все</w>
        <w>закарбувати</w>
        <w>в</w>
        <w>пам'яті</w>
        <g/>
        <pc>:</pc>
        <w>кожен</w>
        <w>день</w>
        <g/>
        <pc>,</pc>
        <w>кожен</w>
        <w>місяць</w>
        <pc>...</pc>
        <pc>"</pc>
        <g/>
        <pc>-</pc>
        <w>поділилася</w>
        <w>Катерина</w>
        <g/>
        <pc>.</pc>
      </p>
      <gap/>
    </chunk>
    <chunk src="http://tabloid.pravda.com.ua/focus/591d5bf35aee8/">
      <gap/>
      <p>
        <pc>"</pc>
        <g/>
        <w>Жінки</w>
        <w>роду</w>
        <w>Джемалятдінових</w>
        <pc>(</pc>
        <g/>
        <w>прізвище</w>
        <w>походить</w>
        <w>від</w>
        <w>імені</w>
        <w>мого</w>
        <w>прадіда</w>
        <w>Джемалятдіна</w>
        <g/>
        <pc>)</pc>
        <w>дуже</w>
        <w>сміливі</w>
        <w>та</w>
        <w>сильні</w>
        <g/>
        <pc>.</pc>
        <w>Прабабуся</w>
        <w>Назил</w>
        <g/>
        <pc>-</pc>
        <g/>
        <w>хан</w>
        <g/>
        <pc>,</pc>
        <w>бабуся</w>
        <w>Едіє</w>
        <g/>
        <pc>...</pc>
        <w>Неймовірні</w>
        <w>жінки</w>
        <g/>
        <pc>,</pc>
        <w>які</w>
        <w>бачили</w>
        <w>смерть</w>
        <g/>
        <pc>,</pc>
        <w>голод</w>
        <g/>
        <pc>,</pc>
        <w>втрачали</w>
        <w>близьких</w>
        <g/>
        <pc>,</pc>
        <w>багато</w>
        <w>працювали</w>
        <g/>
        <pc>,</pc>
        <w>виростили</w>
        <w>і</w>
        <w>гідно</w>
        <w>виховали</w>
        <w>дітей</w>
        <g/>
        <pc>"</pc>
        <g/>
        <pc>,</pc>
        <pc>-</pc>
        <w>написала</w>
        <w>Джамала</w>
        <g/>
        <pc>.</pc>
      </p>
      <gap/>
    </chunk>
    <chunk src="http://playua.net/shhozashou-holistychne-detektyvne-agentstvo-dirka-dzhentli/">
      <gap/>
      <p>
        <w>Дуґлас</w>
        <w>Адамс</w>
        <w>та</w>
        <w>його</w>
        <w>серія</w>
        <w>сатиричних</w>
        <w>романів</w>
        <pc>“</pc>
        <g/>
        <w>Путівник</w>
        <w>Галактикою</w>
        <g/>
        <pc>”</pc>
        <w>в</w>
        <w>свій</w>
        <w>час</w>
        <w>зазнали</w>
        <w>небувалої</w>
        <w>слави</w>
        <w>серед</w>
        <w>прихильників</w>
        <w>наукової</w>
        <w>фантастики</w>
        <g/>
        <pc>.</pc>
        <w>Взявши</w>
        <w>свій</w>
        <w>початок</w>
        <w>у</w>
        <w>форматі</w>
        <w>звичайної</w>
        <w>радіоп’єси</w>
        <g/>
        <pc>,</pc>
        <w>вже</w>
        <w>за</w>
        <w>кілька</w>
        <w>років</w>
        <pc>“</pc>
        <g/>
        <w>путівник</w>
        <g/>
        <pc>”</pc>
        <w>перетворився</w>
        <w>в</w>
        <w>небувалих</w>
        <w>масштабів</w>
        <w>всесвіт</w>
        <g/>
        <pc>,</pc>
        <w>з</w>
        <w>п’ятьма</w>
        <w>книгами</w>
        <w>та</w>
        <w>кіноекранізацією</w>
        <g/>
        <pc>.</pc>
      </p>
      <p>
        <w>Та</w>
        <w>попри</w>
        <w>лаври</w>
        <w>одного</w>
        <w>з</w>
        <w>кращих</w>
        <w>фантастів</w>
        <w>у</w>
        <w>історії</w>
        <g/>
        <pc>,</pc>
        <w>мало</w>
        <w>хто</w>
        <w>знає</w>
        <w>Адамса</w>
        <w>ще</w>
        <w>й</w>
        <w>як</w>
        <w>непоганого</w>
        <w>письменника</w>
        <w>детективного</w>
        <w>жанру</w>
        <g/>
        <pc>.</pc>
        <w>Серія</w>
        <w>книг</w>
        <w>про</w>
        <w>дивакуватого</w>
        <w>та</w>
        <w>ексцентричного</w>
        <w>Дірка</w>
        <w>Джентлі</w>
        <w>взяла</w>
        <w>свій</w>
        <w>початок</w>
        <w>в</w>
        <w>1987</w>
        <pc>(</pc>
        <g/>
        <w>за</w>
        <w>8</w>
        <w>років</w>
        <w>після</w>
        <w>публікації</w>
        <w>добре</w>
        <w>нам</w>
        <w>всім</w>
        <w>відомого</w>
        <pc>“</pc>
        <g/>
        <w>Путівника</w>
        <w>галактикою</w>
        <w>для</w>
        <w>космотуристів</w>
        <g/>
        <pc>”</pc>
        <g/>
        <pc>)</pc>
        <w>з</w>
        <w>романом</w>
        <pc>“</pc>
        <g/>
        <w>Холістичне</w>
        <w>детективне</w>
        <w correct="агентство">агенство</w>
        <w>Дірка</w>
        <w>Джентлі</w>
        <g/>
        <pc>”</pc>
        <g/>
        <pc>,</pc>
        <w>що</w>
        <w>був</w>
        <w>охарактеризований</w>
        <w>близьким</w>
        <w>соратником</w>
        <w>Дугласа</w>
        <g/>
        <pc>,</pc>
        <w>Нілом</w>
        <w>Ґейманом</w>
        <g/>
        <pc>,</pc>
        <w>як</w>
        <pc>“</pc>
        <g/>
        <w>щось</w>
        <w>типу</w>
        <w>привидо</w>
        <g/>
        <pc>-</pc>
        <g/>
        <w>жахастико</w>
        <g/>
        <pc>-</pc>
        <g/>
        <w>часоподорожувально</w>
        <g/>
        <pc>-</pc>
        <g/>
        <w>епічно</w>
        <g/>
        <pc>-</pc>
        <g/>
        <w>романтичної</w>
        <w>комедії</w>
        <w>з</w>
        <w>щіпкою</w>
        <w>бруду</w>
        <g/>
        <pc>,</pc>
        <w>музики</w>
        <w>та</w>
        <w>квантової</w>
        <w>механіки</w>
        <g/>
        <pc>”</pc>
        <g/>
        <pc>.</pc>
        <w>І</w>
        <w>озираючись</w>
        <w>на</w>
        <w>6</w>
        <w>серій</w>
        <w>назад</w>
        <g/>
        <pc>,</pc>
        <w>немає</w>
        <w>нічого</w>
        <g/>
        <pc>,</pc>
        <w>що</w>
        <w>могло</w>
        <w>б</w>
        <w>краще</w>
        <w>описати</w>
        <w>й</w>
        <w>серіал</w>
        <g/>
        <pc>,</pc>
        <w>знятий</w>
        <w>за</w>
        <w>мотивами</w>
        <g/>
        <pc>.</pc>
      </p>
      <gap/>
      <p>
        <w>За</w>
        <w>результатами</w>
        <w>перших</w>
        <w>тижнів</w>
        <w>трансляції</w>
        <g/>
        <pc>,</pc>
        <w>шоу</w>
        <w>не</w>
        <w>викликало</w>
        <w>необхідного</w>
        <w>ажіотажу</w>
        <w>у</w>
        <w>критиків</w>
        <g/>
        <pc>,</pc>
        <w>отримавши</w>
        <w>всього</w>
        <w>68</w>
        <g/>
        <w>%</w>
        <w>позитивних</w>
        <w>рецензій</w>
        <w>на</w>
        <w>RottenTomatoes</w>
        <g/>
        <pc>.</pc>
        <w>Та</w>
        <g/>
        <pc>,</pc>
        <w>як</w>
        <w>це</w>
        <w>часто</w>
        <w>буває</w>
        <w>з</w>
        <w>непересічними</w>
        <w>проектами</w>
        <g/>
        <pc>,</pc>
        <w>публіка</w>
        <w>швидко</w>
        <w>виправила</w>
        <w>помилки</w>
        <w>своїх</w>
        <w>старших</w>
        <w>та</w>
        <w>досвідченіших</w>
        <w>колег</w>
        <g/>
        <pc>,</pc>
        <w>піднявши</w>
        <w>глядацький</w>
        <w>рейтинг</w>
        <w>до</w>
        <w>97</w>
        <g/>
        <w>%</w>
        <g/>
        <pc>.</pc>
        <w>І</w>
        <w>вже</w>
        <w>за</w>
        <w>кілька</w>
        <w>перших</w>
        <w>серій</w>
        <w>знаходиться</w>
        <w>просте</w>
        <w>пояснення</w>
        <w>цьому</w>
        <w>феномену</w>
        <g/>
        <pc>.</pc>
      </p>
      <gap/>
    </chunk>
    <chunk src="http://playua.net/shhozashou-holistychne-detektyvne-agentstvo-dirka-dzhentli/#comment-3134977884">
      <p>
        <w>Класний</w>
        <w>серіал</w>
        <g/>
        <pc>.</pc>
        <w>Ну</w>
        <w>хіба</w>
        <w>трошки</w>
        <w>дивакуватий</w>
        <g/>
        <pc>.</pc>
        <w>:)</w>
        <w>Дивитись</w>
        <w>все</w>
        <w>одно</w>
        <w>приємно</w>
        <g/>
        <pc>,</pc>
        <w>не</w>
        <w>зважаючи</w>
        <w>на</w>
        <w>дивакуватість</w>
        <g/>
        <pc>,</pc>
        <w>майже</w>
        <w>все</w>
        <g/>
        <pc>,</pc>
        <w>окрім</w>
        <w>отої</w>
        <w>серії</w>
        <g/>
        <pc>,</pc>
        <w>де</w>
        <w>Дірк</w>
        <w>і</w>
        <w>Тодд</w>
        <w>по</w>
        <w>лабіринту</w>
        <w>лазять</w>
        <pc>(</pc>
        <g/>
        <w>останній</w>
        <w>скріншот</w>
        <w>в</w>
        <w>статті</w>
        <w>як</w>
        <w>раз</w>
        <w>з</w>
        <w>тої</w>
        <w>серії</w>
        <pc>)</pc>
        <g/>
        <pc>.</pc>
        <w>Як</w>
        <w>мінімум</w>
        <w>з</w>
        <w>минулорічних</w>
        <w>серіалів</w>
        <w>цей</w>
        <w>серіал</w>
        <w>мені</w>
        <w>сподобався</w>
        <w>значно</w>
        <w>більше</w>
        <w>ніж</w>
        <w>марудний</w>
        <w>"Westworld"</w>
        <pc>,</pc>
        <w>який</w>
        <w>усі</w>
        <w>так</w>
        <w>хвалять</w>
        <g/>
        <pc>,</pc>
        <w>і</w>
        <w>в</w>
        <w>якому</w>
        <w>окрім</w>
        <w>останньої</w>
        <w>10-ії</w>
        <w>серії</w>
        <w>дивитись</w>
        <w>майже</w>
        <w>нічого</w>
        <g/>
        <pc>.</pc>
        <w>Бо</w>
        <w>перші</w>
        <w>9</w>
        <w>серій</w>
        <w>практично</w>
        <w>на</w>
        <w>90</w>
        <g/>
        <w>%</w>
        <pc>-</pc>
        <w>дарма</w>
        <w>витрачений</w>
        <w>час</w>
        <g/>
        <pc>,</pc>
        <w>з</w>
        <w>якого</w>
        <w>ні</w>
        <w>інформації</w>
        <w>для</w>
        <w>роздумів</w>
        <g/>
        <pc>,</pc>
        <w>ні</w>
        <w>естетичного</w>
        <w>задоволення</w>
        <w>не</w>
        <w>вдається</w>
        <w>витиснути</w>
        <g/>
        <pc>.</pc>
      </p>
    </chunk>
    <chunk src="http://playua.net/chutky-pro-novu-assassin-s-creed-origins/">
      <gap/>
      <p>
        <w>Безліч</w>
        <w>інформації</w>
        <w>ширилося</w>
        <w>мережею</w>
        <w>про</w>
        <w>нову</w>
        <w>Assassin’s</w>
        <w>Creed</w>
        <g/>
        <pc>,</pc>
        <w>але</w>
        <w>лише</w>
        <w>зараз</w>
        <w>стало</w>
        <w>відомо</w>
        <w>купу</w>
        <w>цікавих</w>
        <w>подробиць</w>
        <g/>
        <pc>.</pc>
        <w>Раніше</w>
        <w>авторитетне</w>
        <w>видання</w>
        <w>Kotaku</w>
        <w>заявляло</w>
        <g/>
        <pc>,</pc>
        <w>що</w>
        <w>наступна</w>
        <w>частина</w>
        <w>серії</w>
        <w>матиме</w>
        <w>підзаголовок</w>
        <w>Empire</w>
        <g/>
        <pc>,</pc>
        <w>а</w>
        <w>події</w>
        <w>гри</w>
        <w>розгортатимуться</w>
        <w>в</w>
        <w>древньому</w>
        <w>Єгипті</w>
        <g/>
        <pc>.</pc>
        <w>Втім</w>
        <g/>
        <pc>,</pc>
        <w>сьогодні</w>
        <w>хлопці</w>
        <w>з</w>
        <w>allgamesdelta</w>
        <w>повідомили</w>
        <w>про</w>
        <w>зовсім</w>
        <w>іншу</w>
        <w>приставку</w>
        <pc>—</pc>
        <w>Origins</w>
        <g/>
        <pc>.</pc>
        <w>Як</w>
        <w>і</w>
        <w>Kotaku</w>
        <g/>
        <pc>,</pc>
        <w>вони</w>
        <w>підтверджують</w>
        <w>інформацію</w>
        <w>про</w>
        <w>Єгипет</w>
        <g/>
        <pc>.</pc>
      </p>
      <gap/>
    </chunk>
    <chunk src="http://playua.net/oglyad-filmu-la-la-land/">
      <gap/>
      <p>
        <w>Весь</w>
        <w>фільм</w>
        <pc>–</pc>
        <w>уклін</w>
        <w>старому</w>
        <w>кіно</w>
        <g/>
        <pc>.</pc>
        <w>Він</w>
        <w>переповнений</w>
        <w>алюзіями</w>
        <w>на</w>
        <w>американські</w>
        <w>та</w>
        <w>французькі</w>
        <w>чорно</w>
        <g/>
        <pc>-</pc>
        <g/>
        <w>білі</w>
        <w>картини</w>
        <g/>
        <pc>,</pc>
        <w>але</w>
        <w>не</w>
        <w>повторює</w>
        <g/>
        <pc>,</pc>
        <w>а</w>
        <w>бережно</w>
        <w>інтерпретує</w>
        <w>їх</w>
        <g/>
        <pc>.</pc>
        <w>Це</w>
        <w>відображено</w>
        <w>в</w>
        <w>самій</w>
        <w>історії</w>
        <w>головного</w>
        <w>героя</w>
        <g/>
        <pc>,</pc>
        <w>який</w>
        <w>молиться</w>
        <w>на</w>
        <w>ікон</w>
        <w>джазу</w>
        <g/>
        <pc>,</pc>
        <w>але</w>
        <w>мусить</w>
        <w>осучаснити</w>
        <w>свою</w>
        <w>музику</w>
        <g/>
        <pc>,</pc>
        <w>щоб</w>
        <w>бути</w>
        <w>актуальним</w>
        <w>сьогодні</w>
        <g/>
        <pc>.</pc>
      </p>
      <gap/>
    </chunk>
    <chunk src="http://playua.net/oglyad-filmu-chomu-vin/">
      <gap/>
      <p>
        <w>Головному</w>
        <w>героєві</w>
        <g/>
        <pc>,</pc>
        <w>мільйонеру</w>
        <g/>
        <pc>,</pc>
        <w>власникові</w>
        <w>ІТ</w>
        <g/>
        <pc>-</pc>
        <g/>
        <w>бізнесу</w>
        <w>відверто</w>
        <w>потурають</w>
        <w>усі</w>
        <w>навколо</w>
        <g/>
        <pc>,</pc>
        <w>підлизуючи</w>
        <w>йому</w>
        <w>де</w>
        <w>не</w>
        <w>ліньки</w>
        <g/>
        <pc>,</pc>
        <w>але</w>
        <w>попри</w>
        <w>це</w>
        <w>герой</w>
        <w>не</w>
        <w>поводить</w>
        <w>себе</w>
        <w>зверхньо</w>
        <w>та</w>
        <w>грубо</w>
        <g/>
        <pc>.</pc>
        <w>Істинна</w>
        <w>картинка</w>
        <w>програмера</w>
        <g/>
        <pc>-</pc>
        <g/>
        <w>генія</w>
        <g/>
        <pc>,</pc>
        <w>яку</w>
        <w>змальовують</w>
        <w>сьогодні</w>
        <w>для</w>
        <w>нас</w>
        <w>біографії</w>
        <w>Возняка</w>
        <g/>
        <pc>,</pc>
        <w>Джобса</w>
        <w>та</w>
        <w>Ґейтса</w>
        <g/>
        <pc>.</pc>
        <w>Це</w>
        <w>не</w>
        <w>природно</w>
        <g/>
        <pc>,</pc>
        <w>але</w>
        <w>очікувано</w>
        <g/>
        <pc>,</pc>
        <w>та</w>
        <w>й</w>
        <w>недоліків</w>
        <w>у</w>
        <w>головному</w>
        <w>героєві</w>
        <w>греблю</w>
        <w>гати</w>
        <g/>
        <pc>,</pc>
        <w>тому</w>
        <w>роздумувати</w>
        <w>над</w>
        <w>тим</w>
        <g/>
        <pc>,</pc>
        <w>чому</w>
        <w>у</w>
        <w>загальному</w>
        <w>компоті</w>
        <w>характеру</w>
        <w>немає</w>
        <w>нахабності</w>
        <g/>
        <pc>,</pc>
        <w>фільм</w>
        <w>не</w>
        <w>дає</w>
        <g/>
        <pc>.</pc>
      </p>
      <p>
        <w>Дуже</w>
        <w>яскраво</w>
        <w>показане</w>
        <w>ставлення</w>
        <w>старого</w>
        <w>покоління</w>
        <w>підприємців</w>
        <w>до</w>
        <w>нового</w>
        <w>на</w>
        <w>межі</w>
        <w>індустріальної</w>
        <w>та</w>
        <w>постіндустріальної</w>
        <w>епохи</w>
        <g/>
        <pc>.</pc>
        <w>Батько</w>
        <g/>
        <pc>,</pc>
        <w>що</w>
        <w>володіє</w>
        <w>друкарською</w>
        <w>фабрикою</w>
        <g/>
        <pc>,</pc>
        <w>відверто</w>
        <w>зневажає</w>
        <w>та</w>
        <w>звинувачує</w>
        <w>молодого</w>
        <w>хлопчину</w>
        <w>за</w>
        <w>те</w>
        <g/>
        <pc>,</pc>
        <w>що</w>
        <w>він</w>
        <pc>“</pc>
        <g/>
        <w>дурить</w>
        <w>людей</w>
        <g/>
        <pc>”</pc>
        <g/>
        <pc>,</pc>
        <pc>“</pc>
        <g/>
        <w>торгує</w>
        <w>повітрям</w>
        <g/>
        <pc>”</pc>
        <g/>
        <pc>,</pc>
        <pc>“</pc>
        <g/>
        <w>весь</w>
        <w>цей</w>
        <w>бізнес</w>
        <pc>–</pc>
        <w>афера</w>
        <g/>
        <pc>,</pc>
        <w>яка</w>
        <w>от</w>
        <g/>
        <pc>-</pc>
        <g/>
        <w>от</w>
        <w>загнеться</w>
        <g/>
        <pc>”</pc>
        <w>і</w>
        <w>все</w>
        <w>в</w>
        <w>такому</w>
        <w>ж</w>
        <w>стилі</w>
        <g/>
        <pc>.</pc>
        <w>Сцени</w>
        <w>фільму</w>
        <w>нагнітають</w>
        <w>контраст</w>
        <w>між</w>
        <w>купами</w>
        <w>офісних</w>
        <w>папірців</w>
        <pc>—</pc>
        <w>і</w>
        <w>безпаперовим</w>
        <w>побутом</w>
        <g/>
        <pc>,</pc>
        <w>японським</w>
        <w>унітазом</w>
        <w>зі</w>
        <w>сенсорним</w>
        <w>змивом</w>
        <w>та</w>
        <w>розумним</w>
        <w>будинком</w>
        <w>із</w>
        <w>Сірі</w>
        <g/>
        <pc>.</pc>
      </p>
      <gap/>
    </chunk>
    <chunk src="http://playua.net/chutky-pro-novu-assassin-s-creed-origins/#comment-3294375711">
      <p>
        <w>Їм</w>
        <w>треба</w>
        <w>частіше</w>
        <w>робити</w>
        <w>такі</w>
        <w>перерви</w>
        <w>між</w>
        <w>іграми</w>
        <w>серії</w>
        <g/>
        <pc>.</pc>
        <w>Зазвичай</w>
        <w>ти</w>
        <w>просто</w>
        <w>бачиш</w>
        <w>нову</w>
        <w>частину</w>
        <w>і</w>
        <w>кажеш</w>
        <pc>-</pc>
        <w>окей</w>
        <g/>
        <pc>,</pc>
        <w>візьму</w>
        <w>якось</w>
        <w>зі</w>
        <w>знижкою</w>
        <g/>
        <pc>.</pc>
        <w>А</w>
        <w>після</w>
        <w>перерви</w>
        <w>хочеться</w>
        <w>брати</w>
        <w>гру</w>
        <w>зразу</w>
        <w>на</w>
        <w>релізі</w>
        <g/>
        <pc>.</pc>
        <w>Дивно</w>
        <w>це</w>
        <w>казати</w>
        <g/>
        <pc>,</pc>
        <w>але</w>
        <w>скучив</w>
        <w>за</w>
        <w>асасінами</w>
        <g/>
        <pc>.</pc>
      </p>
    </chunk>
    <chunk src="http://playua.net/systemni-vymogy-tekken-7/#comment-3320381814">
      <p>
        <w>Механіка</w>
        <w>не</w>
        <w>змінюється</w>
        <g/>
        <pc>,</pc>
        <w>а</w>
        <w>це</w>
        <w>головне</w>
        <g/>
        <pc>.</pc>
        <w>Після</w>
        <w>третьої</w>
        <w>мене</w>
        <w>особисто</w>
        <w>бісили</w>
        <w>інтерактивні</w>
        <w>елементи</w>
        <w>оточення</w>
        <g/>
        <pc>,</pc>
        <w>які</w>
        <w>нах</w>
        <w>не</w>
        <w>впали</w>
        <g/>
        <pc>,</pc>
        <w>але</w>
        <w>це</w>
        <w>дрібниці</w>
        <g/>
        <pc>.</pc>
        <w>Плюс</w>
        <w>кожна</w>
        <w>нова</w>
        <w>частина</w>
        <w>вводила</w>
        <w>нових</w>
        <w>персонажів</w>
        <g/>
        <pc>,</pc>
        <w>не</w>
        <w>всі</w>
        <w>з</w>
        <w>них</w>
        <w>вдалі</w>
        <g/>
        <pc>,</pc>
        <w>на</w>
        <w>мою</w>
        <w>думку</w>
        <g/>
        <pc>,</pc>
        <w>але</w>
        <w>загалом</w>
        <w>рівень</w>
        <w>не</w>
        <w>падав</w>
        <g/>
        <pc>.</pc>
      </p>
    </chunk>
    <chunk src="http://playua.net/systemni-vymogy-tekken-7/#comment-3320385913">
      <p>
        <w>Найголовніше</w>
        <g/>
        <pc>,</pc>
        <w>щоб</w>
        <w>була</w>
        <w>роздільна</w>
        <w>хрестовина</w>
        <g/>
        <pc>.</pc>
        <w>Боївка</w>
        <w>передбачає</w>
        <w>використання</w>
        <w>багатьох</w>
        <w>комбінацій</w>
        <w>рухів</w>
        <w>←</w>
        <g/>
        <pc>,</pc>
        <w>→</w>
        <g/>
        <pc>,</pc>
        <w>↑</w>
        <g/>
        <pc>,</pc>
        <w>↓</w>
        <w>і</w>
        <w>їх</w>
        <w>комбінаторики</w>
        <w>на</w>
        <w>45</w>
        <w>градусів</w>
        <g/>
        <pc>.</pc>
        <w>На</w>
        <w correct="контролері">контроллері</w>
        <w>Xbox</w>
        <w>360</w>
        <g/>
        <pc>,</pc>
        <w>до</w>
        <w>прикладу</w>
        <g/>
        <pc>,</pc>
        <w>хрестовина</w>
        <w>суцільна</w>
        <g/>
        <pc>,</pc>
        <w>дуже</w>
        <w>важко</w>
        <w>точно</w>
        <w>вибирати</w>
        <w>потрібний</w>
        <w correct="напрямок">напрмок</w>
        <g/>
        <pc>,</pc>
        <w>адже</w>
        <w>вона</w>
        <w>часто</w>
        <w>фіксує</w>
        <pc>"</pc>
        <g/>
        <w>ліві</w>
        <g/>
        <pc>"</pc>
        <w>натискання</w>
        <g/>
        <pc>,</pc>
        <w>що</w>
        <w>тригерить</w>
        <w>непотрібну</w>
        <w>комбінацію</w>
        <g/>
        <pc>.</pc>
        <w>Тekken</w>
        <w>в</w>
        <w>першу</w>
        <w>чергу</w>
        <w>ексклюзив</w>
        <w>PS</w>
        <w>і</w>
        <w>завжди</w>
        <w>орієнтувався</w>
        <w>на</w>
        <w>відповідні</w>
        <w correct="контролери">контроллери</w>
        <g/>
        <pc>.</pc>
      </p>
    </chunk>
  </data>
</text>
